MANIFEST.in
README.rst
setup.py
timespan.py
timespan.egg-info/PKG-INFO
timespan.egg-info/SOURCES.txt
timespan.egg-info/dependency_links.txt
timespan.egg-info/top_level.txt