Metadata-Version: 1.0
Name: timespan
Version: 0.1
Summary: Check if timestamp falls within specific boundaries
Home-page: https://github.com/jart/timespan
Author: Justine Tunney
Author-email: jtunney@lobstertech.com
License: MIT
Platform: UNKNOWN
Classifier: Development Status :: 5 - Production/Stable
Classifier: License :: OSI Approved :: MIT License
Classifier: Intended Audience :: Developers
Classifier: Programming Language :: Python
